hamster_cli/__init__.py
hamster_cli/hamster_cli.py
hamster_cli/help_strings.py
hamster_cli-0.12.0.dist-info/DESCRIPTION.rst
hamster_cli-0.12.0.dist-info/METADATA
hamster_cli-0.12.0.dist-info/RECORD
hamster_cli-0.12.0.dist-info/WHEEL
hamster_cli-0.12.0.dist-info/entry_points.txt
hamster_cli-0.12.0.dist-info/metadata.json
hamster_cli-0.12.0.dist-info/top_level.txt
