Metadata-Version: 2.0
Name: hamster-cli
Version: 0.12.0
Summary: A basic CLI for the hamster time tracker.
Home-page: https://github.com/elbenfreund/hamster_cli
Author: Eric Goller
Author-email: Elbenfreund@DenkenInEchtzeit.net
License: GPL3
Keywords: hamster_cli
Platform: UNKNOWN
Classifier: Development Status :: 2 - Pre-Alpha
Classifier: Intended Audience :: End Users/Desktop
Classifier: License :: OSI Approved :: GNU General Public License v3 (GPLv3)
Classifier: Natural Language :: English
Classifier: Programming Language :: Python :: 2
Classifier: Programming Language :: Python :: 2.7
Classifier: Programming Language :: Python :: 3
Classifier: Programming Language :: Python :: 3.4
Requires-Dist: Click
Requires-Dist: appdirs
Requires-Dist: configparser (>=3.5.0b2)
Requires-Dist: future
Requires-Dist: hamsterlib (>=0.1.0)
Requires-Dist: six
Requires-Dist: tabulate
